promptguard/__init__.py
promptguard/authentication.py
promptguard/configuration.py
promptguard/promptguard_service.py
promptguard-0.0.3.dist-info/LICENSE
promptguard-0.0.3.dist-info/METADATA
promptguard-0.0.3.dist-info/WHEEL
promptguard-0.0.3.dist-info/top_level.txt
promptguard-0.0.3.dist-info/RECORD
