Metadata-Version: 2.1
Name: promptguard
Version: 0.0.3
Summary: The client-side SDK for PromptGuard, a privacy layer that enables applications to wrap external provider calls with a sanitization mechanism that hides sensitive inputs via an attested trusted execution environment.
Author-email: Opaque Systems <pypi@opaque.co>
License: Apache License
Project-URL: Homepage, https://github.com/opaque-systems/promptguard-python
Keywords: confidential,llm,ai,generative,security,privacy
Classifier: Programming Language :: Python :: 3
Classifier: License :: OSI Approved :: Apache Software License
Classifier: Operating System :: OS Independent
Requires-Python: >=3.8
License-File: LICENSE
Requires-Dist: pyatls
Requires-Dist: requests >=2.0
